cowswap/__init__.py
cowswap/_constants.py
cowswap/_types.py
cowswap/cowswap.py
cowswap/exceptions.py
cowswap-0.0.1.dist-info/METADATA
cowswap-0.0.1.dist-info/WHEEL
cowswap-0.0.1.dist-info/top_level.txt
cowswap-0.0.1.dist-info/RECORD
